setup.cfg
setup.py
./pedersen/pedersen.py
pedersen/pedersen.py
py_pedersen_commitment.egg-info/PKG-INFO
py_pedersen_commitment.egg-info/SOURCES.txt
py_pedersen_commitment.egg-info/dependency_links.txt
py_pedersen_commitment.egg-info/not-zip-safe
py_pedersen_commitment.egg-info/requires.txt
py_pedersen_commitment.egg-info/top_level.txt